setup.py
base58_encoded/__init__.py
base58_encoded.egg-info/PKG-INFO
base58_encoded.egg-info/SOURCES.txt
base58_encoded.egg-info/dependency_links.txt
base58_encoded.egg-info/not-zip-safe
base58_encoded.egg-info/top_level.txt