Metadata-Version: 1.0
Name: base58-encoded
Version: 0.1
Summary: Encode an integer using base58. You know, for short urls.
Home-page: http://github.com/micahwalter/base58_encoded
Author: Micah Walter
Author-email: micah@micahwalter.com
License: MIT
Platform: UNKNOWN
